os_aaron_alphabet/__init__.py
os_aaron_alphabet-0.0.4.dist-info/LICENSE
os_aaron_alphabet-0.0.4.dist-info/METADATA
os_aaron_alphabet-0.0.4.dist-info/WHEEL
os_aaron_alphabet-0.0.4.dist-info/top_level.txt
os_aaron_alphabet-0.0.4.dist-info/RECORD
